tmagic/__init__.py
tmagic/checker.py
tmagic/exercise.py
tmagic/harness.py
tmagic/pyharness.py
tmagic/rharness.py
tmagic-0.2.0.dist-info/LICENSE
tmagic-0.2.0.dist-info/METADATA
tmagic-0.2.0.dist-info/WHEEL
tmagic-0.2.0.dist-info/top_level.txt
tmagic-0.2.0.dist-info/RECORD
