Metadata-Version: 2.1
Name: tmagic
Version: 0.2.0
Summary: IPython custom cell magic to test Python and R code snippets typed into notebook cells.
Author-email: András Aszódi <andras.aszodi@vbcf.ac.at>
License: Copyright (c) 2018 The Python Packaging Authority
Project-URL: Homepage, https://bitbucket.org/interquadrat/testmagic
Classifier: Programming Language :: Python :: 3
Classifier: License :: OSI Approved :: MIT License
Classifier: Operating System :: OS Independent
Requires-Python: >=3.8
License-File: LICENSE
Requires-Dist: jupyter (>=1.0)
Requires-Dist: ipython (>=6.0)
Requires-Dist: rpy2 (>=3.4)
